alto2txt/__init__.py
alto2txt/extract_publications_text.py
alto2txt/logging_utils.py
alto2txt/multiprocess_xml_to_text.py
alto2txt/spark_xml_to_text.py
alto2txt/xml.py
alto2txt/xml_to_text.py
alto2txt/xml_to_text_entry.py
alto2txt/xml_to_text_entry.py.bak
alto2txt/xslts/__init__.py
alto2txt/xslts/extract_text_bln.xslt
alto2txt/xslts/extract_text_common.xslt
alto2txt/xslts/extract_text_mets13.xslt
alto2txt/xslts/extract_text_mets18.xslt
alto2txt/xslts/extract_text_ukp.xslt
alto2txt-0.3.4.dist-info/LICENSE
alto2txt-0.3.4.dist-info/WHEEL
alto2txt-0.3.4.dist-info/METADATA
alto2txt-0.3.4.dist-info/RECORD
