Metadata-Version: 2.1
Name: alto2txt
Version: 0.3.4
Summary: extract plain text and minimal metadata from ALTO xml files
License: MIT
Author: Mike Jackson
Author-email: mjackson@turing.ac.uk
Requires-Python: >3.7.0
Classifier: License :: OSI Approved :: MIT License
Classifier: Programming Language :: Python :: 3
Classifier: Programming Language :: Python :: 3.10
Classifier: Programming Language :: Python :: 3.8
Classifier: Programming Language :: Python :: 3.9
Requires-Dist: lxml (>=4.7.1,<5.0.0)
